perlin/__init__.py
perlin-0.0.2.dist-info/LICENSE
perlin-0.0.2.dist-info/METADATA
perlin-0.0.2.dist-info/WHEEL
perlin-0.0.2.dist-info/top_level.txt
perlin-0.0.2.dist-info/RECORD
