Metadata-Version: 2.1
Name: perlin
Version: 0.0.2
Summary: A perlin nosie library written in python
Home-page: https://github.com/drakeerv/perlin
Author: Drake Fletcher
Author-email: drakeerv@outlook.com
Maintainer: Drake Fletcher
License: MIT
Download-URL: https://github.com/drakeerv/perlin
Platform: UNKNOWN
Classifier: Programming Language :: Python :: 3
Classifier: Operating System :: OS Independent
Requires-Python: >=2.0
